{
  "entrypoints": {
    "backend": {
      "css": [
        "/system/themes/flexible/backend.f0210c51.css"
      ]
    },
    "confirm": {
      "css": [
        "/system/themes/flexible/confirm.d0c7dee6.css"
      ]
    },
    "conflict": {
      "css": [
        "/system/themes/flexible/conflict.cd089727.css"
      ]
    },
    "diff": {
      "css": [
        "/system/themes/flexible/diff.93d2bbc5.css"
      ]
    },
    "help": {
      "css": [
        "/system/themes/flexible/help.59201ebb.css"
      ]
    },
    "login": {
      "css": [
        "/system/themes/flexible/login.912857f1.css"
      ]
    },
    "popup": {
      "css": [
        "/system/themes/flexible/popup.0e38d1b1.css"
      ]
    },
    "tinymce": {
      "css": [
        "/system/themes/flexible/tinymce.3c7bc5e0.css"
      ]
    },
    "tinymce-dark": {
      "css": [
        "/system/themes/flexible/tinymce-dark.c3737507.css"
      ]
    }
  }
}