{
  "entrypoints": {
    "backend": {
      "css": [
        "/system/themes/flexible/backend.bdbc40bf.css"
      ]
    },
    "confirm": {
      "css": [
        "/system/themes/flexible/confirm.112bee1b.css"
      ]
    },
    "conflict": {
      "css": [
        "/system/themes/flexible/conflict.5d261a60.css"
      ]
    },
    "diff": {
      "css": [
        "/system/themes/flexible/diff.8ff4400b.css"
      ]
    },
    "help": {
      "css": [
        "/system/themes/flexible/help.25ac7a94.css"
      ]
    },
    "login": {
      "css": [
        "/system/themes/flexible/login.51629e5b.css"
      ]
    },
    "popup": {
      "css": [
        "/system/themes/flexible/popup.48817a33.css"
      ]
    },
    "tinymce": {
      "css": [
        "/system/themes/flexible/tinymce.84b1625a.css"
      ]
    },
    "tinymce-dark": {
      "css": [
        "/system/themes/flexible/tinymce-dark.fbda69ff.css"
      ]
    }
  }
}